setup.py
hires/__init__.py
hires/adduct_grouping.py
hires/algorithms.py
hires/feature_detector.py
hires/feature_regrouper.py
hires/shoulder_peak_remover.py
hires.egg-info/PKG-INFO
hires.egg-info/SOURCES.txt
hires.egg-info/dependency_links.txt
hires.egg-info/entry_points.txt
hires.egg-info/top_level.txt