Metadata-Version: 1.0
Name: hires
Version: 0.0.11
Summary: algorithms for high resolution lcms
Home-page: UNKNOWN
Author: Uwe Schmitt
Author-email: uschmitt@uweschmitt.info
License: http://opensource.org/licenses/GPL-3.0
Platform: UNKNOWN
